premoji/.DS_Store
premoji/Mapping.csv
premoji/__init__.py
premoji/emojis_model_19111601.joblib
premoji/predictor_api.py
premoji/models/Mapping.csv
premoji/models/emojis_model_19111601.joblib
premoji-0.1.4.dist-info/LICENSE.txt
premoji-0.1.4.dist-info/METADATA
premoji-0.1.4.dist-info/WHEEL
premoji-0.1.4.dist-info/top_level.txt
premoji-0.1.4.dist-info/RECORD
